{
  "generated_at": "2026-04-20T15:15:22.633573Z",
  "runner_geo": {
    "ip": "135.232.177.176",
    "city": "Chicago",
    "region": "Illinois",
    "country": "US",
    "org": "AS8075 Microsoft Corporation",
    "timezone": "America/Chicago"
  },
  "scrapers": {
    "tpb": [
      {
        "url": "https://thepiratebay.zone",
        "tier": "GOAT",
        "score": 1.0,
        "elo": 1896.9193224253302,
        "avg_response_ms": 286.0160208999936,
        "fallen_comrade": false,
        "last_checked": "2026-04-20T15:14:07.083631Z",
        "cloudflare_detected": false
      },
      {
        "url": "https://thepiratebay.rocks",
        "tier": "GOAT",
        "score": 1.0,
        "elo": 1896.9193224253302,
        "avg_response_ms": 430.07104159999506,
        "fallen_comrade": false,
        "last_checked": "2026-04-20T15:14:10.453582Z",
        "cloudflare_detected": false
      },
      {
        "url": "https://tpb.party",
        "tier": "GOAT",
        "score": 1.0,
        "elo": 1896.9193224253302,
        "avg_response_ms": 494.06965120000086,
        "fallen_comrade": false,
        "last_checked": "2026-04-20T15:14:53.249523Z",
        "cloudflare_detected": false
      },
      {
        "url": "https://thepiratebay10.org",
        "tier": "GOAT",
        "score": 1.0,
        "elo": 1889.4605788569002,
        "avg_response_ms": 851.4866549999895,
        "fallen_comrade": false,
        "last_checked": "2026-04-20T15:15:07.957749Z",
        "cloudflare_detected": false
      },
      {
        "url": "https://thepiratebay.party",
        "tier": "GOAT",
        "score": 1.0,
        "elo": 1886.9098396897218,
        "avg_response_ms": 535.506287499996,
        "fallen_comrade": false,
        "last_checked": "2026-04-20T15:14:02.432463Z",
        "cloudflare_detected": false
      },
      {
        "url": "https://piratebay.party",
        "tier": "GOAT",
        "score": 1.0,
        "elo": 1886.9098396897218,
        "avg_response_ms": 423.5244888999894,
        "fallen_comrade": false,
        "last_checked": "2026-04-20T15:14:29.578117Z",
        "cloudflare_detected": false
      },
      {
        "url": "https://piratebay.live",
        "tier": "GOAT",
        "score": 1.0,
        "elo": 1886.3668360248994,
        "avg_response_ms": 249.88526119999506,
        "fallen_comrade": false,
        "last_checked": "2026-04-20T15:14:26.403304Z",
        "cloudflare_detected": false
      }
    ],
    "annas_archive": [
      {
        "url": "https://annas-archive.gd",
        "tier": "GOAT",
        "score": 1.0,
        "elo": 1797.0768711480582,
        "avg_response_ms": 1564.2343999999957,
        "fallen_comrade": false,
        "last_checked": "2026-04-20T15:14:00.855452Z",
        "cloudflare_detected": false
      }
    ]
  }
}