{
  "generated_at": "2026-03-31T20:39:55.348169Z",
  "runner_geo": {
    "ip": "172.202.102.217",
    "city": "Des Moines",
    "region": "Iowa",
    "country": "US",
    "org": "AS8075 Microsoft Corporation",
    "timezone": "America/Chicago"
  },
  "scrapers": {
    "tpb": [
      {
        "url": "https://thepiratebay.zone",
        "tier": "GOAT",
        "score": 1.0,
        "elo": 1822.2600149070977,
        "avg_response_ms": 258.9751938999974,
        "fallen_comrade": false,
        "last_checked": "2026-03-31T20:39:35.438788Z",
        "cloudflare_detected": false
      },
      {
        "url": "https://thepiratebay.rocks",
        "tier": "GOAT",
        "score": 1.0,
        "elo": 1822.2600149070977,
        "avg_response_ms": 511.4826756999995,
        "fallen_comrade": false,
        "last_checked": "2026-03-31T20:39:39.176785Z",
        "cloudflare_detected": false
      },
      {
        "url": "https://piratebay.live",
        "tier": "GOAT",
        "score": 1.0,
        "elo": 1822.2600149070977,
        "avg_response_ms": 285.9964345000038,
        "fallen_comrade": false,
        "last_checked": "2026-03-31T20:39:40.892009Z",
        "cloudflare_detected": false
      },
      {
        "url": "https://tpb.party",
        "tier": "GOAT",
        "score": 1.0,
        "elo": 1822.2600149070977,
        "avg_response_ms": 321.76882560000024,
        "fallen_comrade": false,
        "last_checked": "2026-03-31T20:39:48.888148Z",
        "cloudflare_detected": false
      },
      {
        "url": "https://thepiratebay10.org",
        "tier": "GOAT",
        "score": 1.0,
        "elo": 1810.7748659572421,
        "avg_response_ms": 337.59483960000057,
        "fallen_comrade": false,
        "last_checked": "2026-03-31T20:39:53.149923Z",
        "cloudflare_detected": false
      },
      {
        "url": "https://thepiratebay.party",
        "tier": "GOAT",
        "score": 1.0,
        "elo": 1806.7874093417192,
        "avg_response_ms": 371.10207520000245,
        "fallen_comrade": false,
        "last_checked": "2026-03-31T20:39:30.721274Z",
        "cloudflare_detected": false
      },
      {
        "url": "https://piratebay.party",
        "tier": "GOAT",
        "score": 1.0,
        "elo": 1806.7874093417192,
        "avg_response_ms": 371.6348574999998,
        "fallen_comrade": false,
        "last_checked": "2026-03-31T20:39:44.922000Z",
        "cloudflare_detected": false
      }
    ],
    "annas_archive": [
      {
        "url": "https://annas-archive.gd",
        "tier": "GOAT",
        "score": 1.0,
        "elo": 1712.7830224204974,
        "avg_response_ms": 1171.9396819000006,
        "fallen_comrade": false,
        "last_checked": "2026-03-31T20:39:30.726618Z",
        "cloudflare_detected": false
      }
    ]
  }
}